<?xml version="1.0" encoding="UTF-8"?>
<Index xmlns="http://www.tso.co.uk/assets/namespace/gazetteindex" editionCode="L" page="032" pageID="https://www.thegazette.co.uk/id/London/index/year/1953/volume/2/page/032" pagePDF="https://www.thegazette.co.uk/London/index/year/1953/volume/2/page/032" pageRDF="https://www.thegazette.co.uk/London/index/year/1953/volume/2/page/032?view=linked-data" type="index" volume="2" year="1953">
  <ItemGroup>
    <MainItem>
      <Key>Carter</Key>
      <Forenames>S. J</Forenames>
      <PageNumber>2191</PageNumber>
    </MainItem>
  </ItemGroup>
  <ItemGroup>
    <MainItem>
      <Key>
        <KeyDitto>___ ___</KeyDitto>
      </Key>
      <Forenames>T. M</Forenames>
      <PageNumber>2479</PageNumber>
    </MainItem>
  </ItemGroup>
  <ItemGroup>
    <MainItem>
      <Key>
        <KeyDitto>___ ___</KeyDitto>
      </Key>
      <Forenames>W. F. N.</Forenames>
      <PageNumber>2102</PageNumber>
    </MainItem>
  </ItemGroup>
  <ItemGroup>
    <MainItem>
      <Key>Cartledge</Key>
      <Forenames>H.</Forenames>
      <PageNumber>2190</PageNumber>
      <PageNumber>2633</PageNumber>
    </MainItem>
  </ItemGroup>
  <ItemGroup>
    <MainItem>
      <Key>Cartwright</Key>
      <Forenames>F. H.</Forenames>
      <Text>(R.A.S.C.)</Text>
      <PageNumber>2191</PageNumber>
    </MainItem>
  </ItemGroup>
  <ItemGroup>
    <MainItem>
      <Key>
        <KeyDitto>___ ___ ___</KeyDitto>
      </Key>
      <Forenames>F. H.</Forenames>
      <Text>(R.E.M.E.)</Text>
      <PageNumber>1863</PageNumber>
    </MainItem>
  </ItemGroup>
  <ItemGroup>
    <MainItem>
      <Key>Carver</Key>
      <Forenames>F. K. M.</Forenames>
      <PageNumber>2104</PageNumber>
    </MainItem>
  </ItemGroup>
  <ItemGroup>
    <MainItem>
      <Key>
        <KeyDitto>___ ___</KeyDitto>
      </Key>
      <Forenames>M. P</Forenames>
      <PageNumber>2411</PageNumber>
    </MainItem>
  </ItemGroup>
  <ItemGroup>
    <MainItem>
      <Key>Caryl</Key>
      <Forenames>H. S. A.</Forenames>
      <PageNumber>2831</PageNumber>
    </MainItem>
  </ItemGroup>
  <ItemGroup>
    <MainItem>
      <Key>Cass</Key>
      <Forenames>W. P</Forenames>
      <PageNumber>2190</PageNumber>
    </MainItem>
  </ItemGroup>
  <ItemGroup>
    <MainItem>
      <Key>Cassidy</Key>
      <Forenames>G. W.</Forenames>
      <PageNumber>3336</PageNumber>
    </MainItem>
  </ItemGroup>
  <ItemGroup>
    <MainItem>
      <Key>Castle</Key>
      <Forenames>D</Forenames>
      <PageNumber>2340</PageNumber>
    </MainItem>
  </ItemGroup>
  <ItemGroup>
    <MainItem>
      <Key>Catchpole</Key>
      <Forenames>G.</Forenames>
      <PageNumber>2481</PageNumber>
    </MainItem>
  </ItemGroup>
  <ItemGroup>
    <MainItem>
      <Key>Catmur</Key>
      <Forenames>D. M. M.</Forenames>
      <PageNumber>3457</PageNumber>
    </MainItem>
  </ItemGroup>
  <ItemGroup>
    <MainItem>
      <Key>Caton</Key>
      <Forenames>J. A</Forenames>
      <PageNumber>2695</PageNumber>
    </MainItem>
  </ItemGroup>
  <ItemGroup>
    <MainItem>
      <Key>Cattanach</Key>
      <Forenames>K. D. H.</Forenames>
      <PageNumber>3027</PageNumber>
    </MainItem>
  </ItemGroup>
  <ItemGroup>
    <MainItem>
      <Key>Cattermole</Key>
      <Forenames>A. V.</Forenames>
      <PageNumber>3336</PageNumber>
    </MainItem>
  </ItemGroup>
  <ItemGroup>
    <MainItem>
      <Key>Catto</Key>
      <Forenames>E. M</Forenames>
      <PageNumber>3335</PageNumber>
    </MainItem>
  </ItemGroup>
  <ItemGroup>
    <MainItem>
      <Key>Cattrall</Key>
      <Forenames>R. W.</Forenames>
      <PageNumber>2566</PageNumber>
    </MainItem>
  </ItemGroup>
  <ItemGroup>
    <MainItem>
      <Key>Cawte</Key>
      <Forenames>J. H</Forenames>
      <PageNumber>2103</PageNumber>
    </MainItem>
  </ItemGroup>
  <ItemGroup>
    <MainItem>
      <Key>
        <KeyDitto>___ ___</KeyDitto>
      </Key>
      <Forenames>Chadwick</Forenames>
      <Text>, E. J</Text>
      <PageNumber>3025</PageNumber>
    </MainItem>
    <SubItem>
      <Text>R. R. C</Text>
      <PageNumber>3263</PageNumber>
    </SubItem>
  </ItemGroup>
  <ItemGroup>
    <MainItem>
      <Key>
        <KeyDitto>___ ___</KeyDitto>
      </Key>
      <Forenames>Chalk</Forenames>
      <Text>, J. H</Text>
      <PageNumber>3151</PageNumber>
    </MainItem>
    <SubItem>
      <Text>K. L. ... :</Text>
      <PageNumber>3210</PageNumber>
    </SubItem>
  </ItemGroup>
  <ItemGroup>
    <MainItem>
      <Key>
        <KeyDitto>___ ___</KeyDitto>
      </Key>
      <Forenames>Chalmers</Forenames>
      <Text>, A. P</Text>
      <PageNumber>2831</PageNumber>
    </MainItem>
    <SubItem>
      <Text>J. D</Text>
      <PageNumber>2105</PageNumber>
    </SubItem>
  </ItemGroup>
  <ItemGroup>
    <MainItem>
      <Key>Chamberlain</Key>
      <Forenames>D. A.</Forenames>
      <PageNumber>3151</PageNumber>
    </MainItem>
  </ItemGroup>
  <ItemGroup>
    <MainItem>
      <Key>Chambers</Key>
      <Forenames>J. V. M.</Forenames>
      <PageNumber>2330</PageNumber>
    </MainItem>
  </ItemGroup>
  <ItemGroup>
    <MainItem>
      <Key>Chambler</Key>
      <Forenames>K.</Forenames>
      <PageNumber>2341</PageNumber>
    </MainItem>
  </ItemGroup>
  <ItemGroup>
    <MainItem>
      <Key>Chandler</Key>
      <Forenames>E. J.</Forenames>
      <PageNumber>2482</PageNumber>
    </MainItem>
  </ItemGroup>
  <ItemGroup>
    <MainItem>
      <Key>
        <KeyDitto>___ ___</KeyDitto>
      </Key>
      <Forenames>J. C</Forenames>
      <PageNumber>3522</PageNumber>
    </MainItem>
  </ItemGroup>
  <ItemGroup>
    <MainItem>
      <Key>
        <KeyDitto>___ ___</KeyDitto>
      </Key>
      <Forenames>P. M</Forenames>
      <PageNumber>3521</PageNumber>
    </MainItem>
  </ItemGroup>
  <ItemGroup>
    <MainItem>
      <Key>Chandrabahadur</Key>
      <Forenames>Gurung</Forenames>
      <PageNumber>3150</PageNumber>
    </MainItem>
  </ItemGroup>
  <ItemGroup>
    <MainItem>
      <Key>Chandrabahadur</Key>
      <Forenames>Rai</Forenames>
      <PageNumber>3600</PageNumber>
    </MainItem>
  </ItemGroup>
  <ItemGroup>
    <MainItem>
      <Key>Chandrasing</Key>
      <Title>Thapa .</Title>
      <PageNumber>3206</PageNumber>
    </MainItem>
  </ItemGroup>
  <ItemGroup>
    <MainItem>
      <Key>Channer</Key>
      <Forenames>H. K. de R</Forenames>
      <PageNumber>2635</PageNumber>
    </MainItem>
  </ItemGroup>
  <ItemGroup>
    <MainItem>
      <Key>Chanter</Key>
      <Forenames>J. B</Forenames>
      <PageNumber>1963</PageNumber>
    </MainItem>
  </ItemGroup>
  <ItemGroup>
    <MainItem>
      <Key>Chapman</Key>
      <Forenames>D. R. J.</Forenames>
      <PageNumber>3520</PageNumber>
    </MainItem>
  </ItemGroup>
  <ItemGroup>
    <MainItem>
      <Key>
        <KeyDitto>___ ___</KeyDitto>
      </Key>
      <Forenames>J. J</Forenames>
      <PageNumber>861</PageNumber>
    </MainItem>
  </ItemGroup>
  <ItemGroup>
    <MainItem>
      <Key>
        <KeyDitto>___ ___</KeyDitto>
      </Key>
      <Forenames>J. B.</Forenames>
      <PageNumber>3457</PageNumber>
    </MainItem>
  </ItemGroup>
  <ItemGroup>
    <MainItem>
      <Key>
        <KeyDitto>___ ___ ___</KeyDitto>
      </Key>
      <Forenames>J. L.</Forenames>
      <PageNumber>2895</PageNumber>
    </MainItem>
  </ItemGroup>
  <ItemGroup>
    <MainItem>
      <Key>
        <KeyDitto>___ ___</KeyDitto>
      </Key>
      <Forenames>P. J.</Forenames>
      <PageNumber>3521</PageNumber>
    </MainItem>
  </ItemGroup>
  <ItemGroup>
    <MainItem>
      <Key>
        <KeyDitto>___ ___</KeyDitto>
      </Key>
      <Forenames>R. P.</Forenames>
      <PageNumber>3335</PageNumber>
    </MainItem>
  </ItemGroup>
  <ItemGroup>
    <MainItem>
      <Key>
        <KeyDitto>___ ___</KeyDitto>
      </Key>
      <Forenames>T. J.</Forenames>
      <PageNumber>3209</PageNumber>
    </MainItem>
  </ItemGroup>
  <ItemGroup>
    <MainItem>
      <Key>
        <KeyDitto>___ ___ ___</KeyDitto>
      </Key>
      <Forenames>T. W.</Forenames>
      <PageNumber>2104</PageNumber>
    </MainItem>
  </ItemGroup>
  <ItemGroup>
    <MainItem>
      <Key>
        <KeyDitto>___ ___</KeyDitto>
      </Key>
      <Forenames>V. W. J.</Forenames>
      <PageNumber>3333</PageNumber>
    </MainItem>
  </ItemGroup>
  <ItemGroup>
    <MainItem>
      <Key>Chappell</Key>
      <Forenames>R. O.</Forenames>
      <PageNumber>2483</PageNumber>
    </MainItem>
  </ItemGroup>
  <ItemGroup>
    <MainItem>
      <Key>Chappie</Key>
      <Forenames>L. G.</Forenames>
      <PageNumber>1932</PageNumber>
    </MainItem>
  </ItemGroup>
  <ItemGroup>
    <MainItem>
      <Key>
        <KeyDitto>___ ___ ___</KeyDitto>
      </Key>
      <Forenames>M. T.</Forenames>
      <PageNumber>3337</PageNumber>
    </MainItem>
  </ItemGroup>
  <ItemGroup>
    <MainItem>
      <Key>Charles</Key>
      <Forenames>A. H.</Forenames>
      <PageNumber>2410</PageNumber>
    </MainItem>
  </ItemGroup>
  <ItemGroup>
    <MainItem>
      <Key>Charlesworth</Key>
      <Forenames>T.</Forenames>
      <PageNumber>2481</PageNumber>
    </MainItem>
  </ItemGroup>
  <ItemGroup>
    <MainItem>
      <Key>Charlton</Key>
      <Forenames>J. A.</Forenames>
      <PageNumber>3265</PageNumber>
    </MainItem>
  </ItemGroup>
  <ItemGroup>
    <MainItem>
      <Key>Charrot</Key>
      <Forenames>A. C.</Forenames>
      <PageNumber>2896</PageNumber>
    </MainItem>
  </ItemGroup>
  <ItemGroup>
    <MainItem>
      <Key>Charters</Key>
      <Forenames>R. P.</Forenames>
      <PageNumber>2104</PageNumber>
    </MainItem>
  </ItemGroup>
  <ItemGroup>
    <MainItem>
      <Key>Chase</Key>
      <Forenames>A. W.</Forenames>
      <PageNumber>2255</PageNumber>
    </MainItem>
  </ItemGroup>
  <ItemGroup>
    <MainItem>
      <Key>Chatfield</Key>
      <Forenames>J. M.</Forenames>
      <PageNumber>2634</PageNumber>
    </MainItem>
  </ItemGroup>
  <ItemGroup>
    <MainItem>
      <Key>Chayen</Key>
      <Forenames>M. J.</Forenames>
      <PageNumber>2103</PageNumber>
    </MainItem>
  </ItemGroup>
  <ItemGroup>
    <MainItem>
      <Key>Cheetham</Key>
      <Forenames>P. E.</Forenames>
      <PageNumber>3210</PageNumber>
    </MainItem>
  </ItemGroup>
  <ItemGroup>
    <MainItem>
      <Key>Cheshire</Key>
      <Forenames>W. R.</Forenames>
      <PageNumber>2832</PageNumber>
    </MainItem>
  </ItemGroup>
  <ItemGroup>
    <MainItem>
      <Key>Chester</Key>
      <Forenames>J.</Forenames>
      <PageNumber>1933</PageNumber>
    </MainItem>
  </ItemGroup>
  <ItemGroup>
    <MainItem>
      <Key>
        <KeyDitto>___ ___</KeyDitto>
      </Key>
      <Forenames>W. H.</Forenames>
      <PageNumber>3334</PageNumber>
    </MainItem>
  </ItemGroup>
  <ItemGroup>
    <MainItem>
      <Key>Chestnutt</Key>
      <Forenames>J. M. A.</Forenames>
      <PageNumber>2695</PageNumber>
    </MainItem>
  </ItemGroup>
  <ItemGroup>
    <MainItem>
      <Key>Chettle</Key>
      <Forenames>C.</Forenames>
      <PageNumber>3393</PageNumber>
    </MainItem>
  </ItemGroup>
  <ItemGroup>
    <MainItem>
      <Key>Chevalier</Key>
      <Forenames>P. J. H.</Forenames>
      <PageNumber>3333</PageNumber>
    </MainItem>
  </ItemGroup>
  <ItemGroup>
    <MainItem>
      <Key>Chew</Key>
      <Forenames>P. H.</Forenames>
      <PageNumber>3601</PageNumber>
    </MainItem>
  </ItemGroup>
  <ItemGroup>
    <MainItem>
      <Key>Chhatraman</Key>
      <Forenames>Rai</Forenames>
      <PageNumber>3262</PageNumber>
      <PageNumber>3262</PageNumber>
    </MainItem>
  </ItemGroup>
  <ItemGroup>
    <MainItem>
      <Key>Chichester</Key>
      <Forenames>O. R. H.</Forenames>
      <PageNumber>3097</PageNumber>
    </MainItem>
  </ItemGroup>
  <ItemGroup>
    <MainItem>
      <Key>Childs</Key>
      <Forenames>A. H. B</Forenames>
      <Text>,</Text>
      <PageNumber>3151</PageNumber>
    </MainItem>
  </ItemGroup>
  <ItemGroup>
    <MainItem>
      <Key>
        <KeyDitto>___ ___</KeyDitto>
      </Key>
      <Forenames>D. W.</Forenames>
      <PageNumber>3208</PageNumber>
    </MainItem>
  </ItemGroup>
  <ItemGroup>
    <MainItem>
      <Key>Chilvers</Key>
      <Forenames>D. R.</Forenames>
      <PageNumber>2341</PageNumber>
    </MainItem>
  </ItemGroup>
  <ItemGroup>
    <MainItem>
      <Key>Chipp</Key>
      <Forenames>R. N.</Forenames>
      <PageNumber>3262</PageNumber>
    </MainItem>
  </ItemGroup>
  <ItemGroup>
    <MainItem>
      <Key>Chipping</Key>
      <Forenames>N. J.</Forenames>
      <PageNumber>3336</PageNumber>
    </MainItem>
  </ItemGroup>
  <ItemGroup>
    <MainItem>
      <Key>Chirnside</Key>
      <Forenames>H. W.</Forenames>
      <PageNumber>2480</PageNumber>
    </MainItem>
  </ItemGroup>
  <ItemGroup>
    <MainItem>
      <Key>Chitrabahadur</Key>
      <Forenames>Thapa</Forenames>
      <Text>(</Text>
      <PageNumber>2</PageNumber>
    </MainItem>
  </ItemGroup>
  <ItemGroup>
    <MainItem>
      <Key>Chitrabahadur</Key>
      <Forenames>Thapa</Forenames>
      <Text>(</Text>
      <PageNumber>6</PageNumber>
    </MainItem>
  </ItemGroup>
  <ItemGroup>
    <MainItem>
      <Key>Chittenden</Key>
      <Forenames>S. F.</Forenames>
      <PageNumber>3458</PageNumber>
    </MainItem>
  </ItemGroup>
  <ItemGroup>
    <MainItem>
      <Key>Chitty</Key>
      <Forenames>T. D.</Forenames>
      <PageNumber>3025</PageNumber>
    </MainItem>
  </ItemGroup>
  <ItemGroup>
    <MainItem>
      <Key>Christie-Miller</Key>
      <Forenames>D. G.</Forenames>
      <PageNumber>2341</PageNumber>
    </MainItem>
  </ItemGroup>
  <ItemGroup>
    <MainItem>
      <Key>Christopherson</Key>
      <Forenames>M.</Forenames>
      <PageNumber>2035</PageNumber>
    </MainItem>
  </ItemGroup>
  <ItemGroup>
    <MainItem>
      <Key>Chudley</Key>
      <Forenames>F. J.</Forenames>
      <PageNumber>3263</PageNumber>
    </MainItem>
  </ItemGroup>
  <ItemGroup>
    <MainItem>
      <Key>Christie</Key>
      <Forenames>P. G. B.</Forenames>
      <PageNumber>3208</PageNumber>
    </MainItem>
  </ItemGroup>
  <ItemGroup>
    <MainItem>
      <Key>
        <KeyDitto>___ ___ ___</KeyDitto>
      </Key>
      <Forenames>T. J. C.</Forenames>
      <PageNumber>3336</PageNumber>
    </MainItem>
  </ItemGroup>
  <ItemGroup>
    <MainItem>
      <Key>Churcher</Key>
      <Forenames>J. L.</Forenames>
      <PageNumber>3335</PageNumber>
    </MainItem>
  </ItemGroup>
  <ItemGroup>
    <MainItem>
      <Key>Chynoweth</Key>
      <Forenames>J. D.</Forenames>
      <PageNumber>2191</PageNumber>
    </MainItem>
  </ItemGroup>
  <ItemGroup>
    <MainItem>
      <Key>Clapham</Key>
      <Forenames>C. C.</Forenames>
      <PageNumber>2831</PageNumber>
    </MainItem>
  </ItemGroup>
  <ItemGroup>
    <MainItem>
      <Key>
        <KeyDitto>___ ___</KeyDitto>
      </Key>
      <Forenames>E. E.</Forenames>
      <PageNumber>2896</PageNumber>
    </MainItem>
  </ItemGroup>
  <ItemGroup>
    <MainItem>
      <Key>Clapton</Key>
      <Forenames>E. L.</Forenames>
      <PageNumber>2188</PageNumber>
    </MainItem>
  </ItemGroup>
  <ItemGroup>
    <MainItem>
      <Key>Clare</Key>
      <Forenames>R. J.</Forenames>
      <PageNumber>2257</PageNumber>
    </MainItem>
  </ItemGroup>
  <ItemGroup>
    <MainItem>
      <Key>Clark</Key>
      <Forenames>A. T.</Forenames>
      <PageNumber>3264</PageNumber>
    </MainItem>
  </ItemGroup>
  <ItemGroup>
    <MainItem>
      <Key>
        <KeyDitto>___ ___</KeyDitto>
      </Key>
      <Forenames>B. A.</Forenames>
      <PageNumber>2829</PageNumber>
    </MainItem>
  </ItemGroup>
  <ItemGroup>
    <MainItem>
      <Key>
        <KeyDitto>___ ___</KeyDitto>
      </Key>
      <Forenames>C. D. L.</Forenames>
      <PageNumber>2034</PageNumber>
    </MainItem>
  </ItemGroup>
  <ItemGroup>
    <MainItem>
      <Key>
        <KeyDitto>___ ___</KeyDitto>
      </Key>
      <Forenames>I. L.</Forenames>
      <PageNumber>1934</PageNumber>
    </MainItem>
  </ItemGroup>
  <ItemGroup>
    <MainItem>
      <Key>
        <KeyDitto>___ ___</KeyDitto>
      </Key>
      <Forenames>J. G. H.</Forenames>
      <PageNumber>3457</PageNumber>
    </MainItem>
  </ItemGroup>
  <ItemGroup>
    <MainItem>
      <Key>
        <KeyDitto>___ ___</KeyDitto>
      </Key>
      <Forenames>P. G. D.</Forenames>
      <PageNumber>2697</PageNumber>
    </MainItem>
  </ItemGroup>
  <ItemGroup>
    <MainItem>
      <Key>
        <KeyDitto>___ ___</KeyDitto>
      </Key>
      <Forenames>R. G.</Forenames>
      <PageNumber>2341</PageNumber>
    </MainItem>
  </ItemGroup>
  <ItemGroup>
    <MainItem>
      <Key>
        <KeyDitto>___ ___</KeyDitto>
      </Key>
      <Forenames>R. N.</Forenames>
      <PageNumber>2101</PageNumber>
    </MainItem>
  </ItemGroup>
  <ItemGroup>
    <MainItem>
      <Key>
        <KeyDitto>___ ___ ___</KeyDitto>
      </Key>
      <Forenames>R. Q.</Forenames>
      <Text>, Corr</Text>
      <PageNumber>3337</PageNumber>
    </MainItem>
  </ItemGroup>
  <ItemGroup>
    <MainItem>
      <Key>
        <KeyDitto>___ ___</KeyDitto>
      </Key>
      <Forenames>W. H.</Forenames>
      <PageNumber>2830</PageNumber>
      <PageNumber>2830</PageNumber>
    </MainItem>
  </ItemGroup>
  <ItemGroup>
    <MainItem>
      <Key>Clarke</Key>
      <Forenames>B.</Forenames>
      <PageNumber>2190</PageNumber>
    </MainItem>
  </ItemGroup>
  <ItemGroup>
    <MainItem>
      <Key>
        <KeyDitto>___ ___</KeyDitto>
      </Key>
      <Forenames>E.</Forenames>
      <PageNumber>2829</PageNumber>
    </MainItem>
  </ItemGroup>
  <ItemGroup>
    <MainItem>
      <Key>
        <KeyDitto>___ ___</KeyDitto>
      </Key>
      <Forenames>E. N.</Forenames>
      <PageNumber>2829</PageNumber>
    </MainItem>
  </ItemGroup>
  <ItemGroup>
    <MainItem>
      <Key>
        <KeyDitto>___ ___</KeyDitto>
      </Key>
      <Forenames>E. W.</Forenames>
      <PageNumber>2410</PageNumber>
    </MainItem>
  </ItemGroup>
  <ItemGroup>
    <MainItem>
      <Key>
        <KeyDitto>___</KeyDitto>
      </Key>
      <Forenames>F. R.</Forenames>
      <PageNumber>2188</PageNumber>
    </MainItem>
  </ItemGroup>
  <ItemGroup>
    <MainItem>
      <Key>
        <KeyDitto>___ ___</KeyDitto>
      </Key>
      <Forenames>F. W.</Forenames>
      <PageNumber>2829</PageNumber>
    </MainItem>
  </ItemGroup>
  <ItemGroup>
    <MainItem>
      <Key>
        <KeyDitto>___ ___</KeyDitto>
      </Key>
      <Forenames>G.</Forenames>
      <PageNumber>3100</PageNumber>
    </MainItem>
  </ItemGroup>
  <ItemGroup>
    <MainItem>
      <Key>
        <KeyDitto>___ ___</KeyDitto>
      </Key>
      <Forenames>G. H.</Forenames>
      <PageNumber>3393</PageNumber>
    </MainItem>
  </ItemGroup>
  <ItemGroup>
    <MainItem>
      <Key>
        <KeyDitto>___ ___</KeyDitto>
      </Key>
      <Forenames>H. L.</Forenames>
      <PageNumber>3601</PageNumber>
    </MainItem>
  </ItemGroup>
  <ItemGroup>
    <MainItem>
      <Key>
        <KeyDitto>___ ___ ___</KeyDitto>
      </Key>
      <Forenames>H. W.</Forenames>
      <PageNumber>2034</PageNumber>
    </MainItem>
  </ItemGroup>
  <ItemGroup>
    <MainItem>
      <Key>
        <KeyDitto>___ ___ ___</KeyDitto>
      </Key>
      <Forenames>J. A. G.</Forenames>
      <PageNumber>1965</PageNumber>
    </MainItem>
  </ItemGroup>
  <ItemGroup>
    <MainItem>
      <Key>
        <KeyDitto>___ ___</KeyDitto>
      </Key>
      <Forenames>J. M.</Forenames>
      <PageNumber>3457</PageNumber>
    </MainItem>
  </ItemGroup>
  <ItemGroup>
    <MainItem>
      <Key>
        <KeyDitto>___ ___</KeyDitto>
      </Key>
      <Forenames>J. W.</Forenames>
      <PageNumber>3263</PageNumber>
    </MainItem>
  </ItemGroup>
  <ItemGroup>
    <MainItem>
      <Key>
        <KeyDitto>___ ___</KeyDitto>
      </Key>
      <Forenames>K. H.</Forenames>
      <PageNumber>1965</PageNumber>
    </MainItem>
  </ItemGroup>
  <ItemGroup>
    <MainItem>
      <Key>
        <KeyDitto>___ ___</KeyDitto>
      </Key>
      <Forenames>M. A. N.</Forenames>
      <PageNumber>2034</PageNumber>
    </MainItem>
  </ItemGroup>
  <ItemGroup>
    <MainItem>
      <Key>
        <KeyDitto>___ ___</KeyDitto>
      </Key>
      <Forenames>P. R .</Forenames>
      <PageNumber>3457</PageNumber>
    </MainItem>
  </ItemGroup>
  <ItemGroup>
    <MainItem>
      <Key>
        <KeyDitto>___ ___</KeyDitto>
      </Key>
      <Forenames>R. W. H.</Forenames>
      <PageNumber>2831</PageNumber>
    </MainItem>
  </ItemGroup>
  <ItemGroup>
    <MainItem>
      <Key>Clarkson</Key>
      <Forenames>F. L.</Forenames>
      <PageNumber>2895</PageNumber>
    </MainItem>
  </ItemGroup>
  <ItemGroup>
    <MainItem>
      <Key>Clarry</Key>
      <Forenames>J. H.</Forenames>
      <PageNumber>2034</PageNumber>
    </MainItem>
  </ItemGroup>
  <ItemGroup>
    <MainItem>
      <Key>Clary</Key>
      <Forenames>D. W.</Forenames>
      <PageNumber>3520</PageNumber>
    </MainItem>
  </ItemGroup>
  <ItemGroup>
    <MainItem>
      <Key>Claypole</Key>
      <Forenames>P.</Forenames>
      <PageNumber>3521</PageNumber>
    </MainItem>
  </ItemGroup>
  <ItemGroup>
    <MainItem>
      <Key>Clayton</Key>
      <Forenames>D. J.</Forenames>
      <PageNumber>3458</PageNumber>
    </MainItem>
  </ItemGroup>
  <ItemGroup>
    <MainItem>
      <Key>
        <KeyDitto>___ ___</KeyDitto>
      </Key>
      <Forenames>J. S.</Forenames>
      <PageNumber>2768</PageNumber>
    </MainItem>
  </ItemGroup>
  <ItemGroup>
    <MainItem>
      <Key>Cleave</Key>
      <Forenames>J. H.</Forenames>
      <PageNumber>2635</PageNumber>
    </MainItem>
  </ItemGroup>
  <ItemGroup>
    <MainItem>
      <Key>Cleeves</Key>
      <Forenames>R. H. E.</Forenames>
      <PageNumber>2191</PageNumber>
    </MainItem>
  </ItemGroup>
  <ItemGroup>
    <MainItem>
      <Key>Clegg</Key>
      <Forenames>H.</Forenames>
      <PageNumber>2480</PageNumber>
    </MainItem>
  </ItemGroup>
  <ItemGroup>
    <MainItem>
      <Key>
        <KeyDitto>___ ___ ___</KeyDitto>
      </Key>
      <Forenames>M. A.</Forenames>
      <PageNumber>2635</PageNumber>
    </MainItem>
  </ItemGroup>
  <ItemGroup>
    <MainItem>
      <Key>Clement</Key>
      <Forenames>J.</Forenames>
      <Text>, Coir</Text>
      <PageNumber>1964</PageNumber>
    </MainItem>
  </ItemGroup>
  <ItemGroup>
    <MainItem>
      <Key>Clements</Key>
      <Forenames>D. C. H.</Forenames>
      <PageNumber>2104</PageNumber>
      <PageNumber>2104</PageNumber>
    </MainItem>
  </ItemGroup>
  <ItemGroup>
    <MainItem>
      <Key>
        <KeyDitto>___ ___</KeyDitto>
      </Key>
      <Forenames>J. E.</Forenames>
      <PageNumber>2256</PageNumber>
    </MainItem>
  </ItemGroup>
  <ItemGroup>
    <MainItem>
      <Key>Clemow</Key>
      <Forenames>J.</Forenames>
      <PageNumber>3099</PageNumber>
    </MainItem>
  </ItemGroup>
  <ItemGroup>
    <MainItem>
      <Key>Cleverly</Key>
      <Forenames>J. G.</Forenames>
      <PageNumber>1932</PageNumber>
    </MainItem>
  </ItemGroup>
  <ItemGroup>
    <MainItem>
      <Key>Cliff</Key>
      <Forenames>W. H.</Forenames>
      <PageNumber>2034</PageNumber>
    </MainItem>
  </ItemGroup>
  <ItemGroup>
    <MainItem>
      <Key>Cliffe</Key>
      <Forenames>E. E.</Forenames>
      <PageNumber>2341</PageNumber>
    </MainItem>
  </ItemGroup>
  <ItemGroup>
    <MainItem>
      <Key>Clifford</Key>
      <Forenames>C. C.</Forenames>
      <PageNumber>3263</PageNumber>
    </MainItem>
  </ItemGroup>
  <ItemGroup>
    <MainItem>
      <Key>
        <KeyDitto>___ ___</KeyDitto>
      </Key>
      <Forenames>D. M.</Forenames>
      <PageNumber>2035</PageNumber>
    </MainItem>
  </ItemGroup>
  <ItemGroup>
    <MainItem>
      <Key>
        <KeyDitto>___ ___</KeyDitto>
      </Key>
      <Forenames>E. H. M.</Forenames>
      <PageNumber>2103</PageNumber>
    </MainItem>
  </ItemGroup>
  <ItemGroup>
    <MainItem>
      <Key>
        <KeyDitto>___ ___</KeyDitto>
      </Key>
      <Forenames>J. E.</Forenames>
      <PageNumber>2635</PageNumber>
    </MainItem>
  </ItemGroup>
  <ItemGroup>
    <MainItem>
      <Key>Clift</Key>
      <Forenames>D. A. W.</Forenames>
      <PageNumber>3456</PageNumber>
    </MainItem>
  </ItemGroup>
  <ItemGroup>
    <MainItem>
      <Key>
        <KeyDitto>___</KeyDitto>
      </Key>
      <Forenames>J. M.</Forenames>
      <PageNumber>2189</PageNumber>
    </MainItem>
  </ItemGroup>
  <ItemGroup>
    <MainItem>
      <Key>Clifton</Key>
      <Forenames>N. F.</Forenames>
      <PageNumber>3262</PageNumber>
    </MainItem>
  </ItemGroup>
  <ItemGroup>
    <MainItem>
      <Key>Close-Brooks</Key>
      <Forenames>N. B</Forenames>
      <PageNumber>2104</PageNumber>
    </MainItem>
  </ItemGroup>
  <ItemGroup>
    <MainItem>
      <Key>Clowes</Key>
      <Forenames>B.</Forenames>
      <PageNumber>2256</PageNumber>
    </MainItem>
  </ItemGroup>
  <ItemGroup>
    <MainItem>
      <Key>
        <KeyDitto>___ ___</KeyDitto>
      </Key>
      <Forenames>J. A. Clutterbuck</Forenames>
      <Text>, E. W. C</Text>
      <PageNumber>1963</PageNumber>
    </MainItem>
  </ItemGroup>
  <ItemGroup>
    <MainItem>
      <Key>
        <KeyDitto>___ ___</KeyDitto>
      </Key>
      <Forenames>J. E</Forenames>
      <PageNumber>2567</PageNumber>
    </MainItem>
  </ItemGroup>
  <ItemGroup>
    <MainItem>
      <Key>Cobb</Key>
      <Forenames>B. F. A.</Forenames>
      <PageNumber>3335</PageNumber>
    </MainItem>
  </ItemGroup>
  <ItemGroup>
    <MainItem>
      <Key>Cobbina</Key>
      <Forenames>J.</Forenames>
      <Text>,H</Text>
      <PageNumber>2341</PageNumber>
    </MainItem>
  </ItemGroup>
  <ItemGroup>
    <MainItem>
      <Key>Cobbold</Key>
      <Forenames>R. V .</Forenames>
      <PageNumber>1862</PageNumber>
    </MainItem>
  </ItemGroup>
  <ItemGroup>
    <MainItem>
      <Key>Cochrane</Key>
      <Forenames>A. J. C.</Forenames>
      <PageNumber>3601</PageNumber>
    </MainItem>
  </ItemGroup>
  <ItemGroup>
    <MainItem>
      <Key>Cockburn</Key>
      <Forenames>R. C.</Forenames>
      <PageNumber>3099</PageNumber>
    </MainItem>
  </ItemGroup>
  <ItemGroup>
    <MainItem>
      <Key>
        <KeyDitto>___ ___</KeyDitto>
      </Key>
      <Forenames>R. N</Forenames>
      <PageNumber>3456</PageNumber>
    </MainItem>
  </ItemGroup>
  <ItemGroup>
    <MainItem>
      <Key>
        <KeyDitto>___ ___</KeyDitto>
      </Key>
      <Forenames>W. B</Forenames>
      <PageNumber>3600</PageNumber>
    </MainItem>
  </ItemGroup>
  <ItemGroup>
    <MainItem>
      <Key>Cocks</Key>
      <Forenames>P. J</Forenames>
      <PageNumber>2190</PageNumber>
    </MainItem>
  </ItemGroup>
  <ItemGroup>
    <MainItem>
      <Key>Cocquerel</Key>
      <Forenames>C. T.</Forenames>
      <PageNumber>3336</PageNumber>
    </MainItem>
  </ItemGroup>
  <ItemGroup>
    <MainItem>
      <Key>Codd</Key>
      <Forenames>P</Forenames>
      <PageNumber>2482</PageNumber>
    </MainItem>
  </ItemGroup>
  <ItemGroup>
    <MainItem>
      <Key>Codner</Key>
      <Forenames>T. D. O.</Forenames>
      <PageNumber>2829</PageNumber>
    </MainItem>
  </ItemGroup>
  <ItemGroup>
    <MainItem>
      <Key>Codrington</Key>
      <Forenames>C. G.</Forenames>
      <PageNumber>3601</PageNumber>
    </MainItem>
  </ItemGroup>
  <ItemGroup>
    <MainItem>
      <Key>
        <KeyDitto>___ ___ ___</KeyDitto>
      </Key>
      <Forenames>M. C. A.</Forenames>
      <PageNumber>2479</PageNumber>
    </MainItem>
  </ItemGroup>
  <ItemGroup>
    <MainItem>
      <Key>Coe</Key>
      <Forenames>J. T</Forenames>
      <PageNumber>2896</PageNumber>
    </MainItem>
  </ItemGroup>
  <ItemGroup>
    <MainItem>
      <Key>Coffey</Key>
      <Forenames>J. J.</Forenames>
      <PageNumber>2340</PageNumber>
    </MainItem>
  </ItemGroup>
  <ItemGroup>
    <MainItem>
      <Key>Cohen</Key>
      <Forenames>I. H</Forenames>
      <PageNumber>2635</PageNumber>
    </MainItem>
  </ItemGroup>
  <ItemGroup>
    <MainItem>
      <Key>Coke</Key>
      <Forenames>S</Forenames>
      <PageNumber>2192</PageNumber>
    </MainItem>
  </ItemGroup>
  <ItemGroup>
    <MainItem>
      <Key>Colan</Key>
      <Forenames>P. W. C.</Forenames>
      <PageNumber>3151</PageNumber>
    </MainItem>
  </ItemGroup>
  <ItemGroup>
    <MainItem>
      <Key>Coldrey</Key>
      <Forenames>J. B.</Forenames>
      <PageNumber>1933</PageNumber>
    </MainItem>
  </ItemGroup>
  <ItemGroup>
    <MainItem>
      <Key>Coldstream</Key>
      <Forenames>G. A. P.</Forenames>
      <PageNumber>1966</PageNumber>
    </MainItem>
  </ItemGroup>
  <ItemGroup>
    <MainItem>
      <Key>
        <KeyDitto>___ ___ ___</KeyDitto>
      </Key>
      <Forenames>R. A. C.</Forenames>
      <PageNumber>2695</PageNumber>
    </MainItem>
  </ItemGroup>
  <ItemGroup>
    <MainItem>
      <Key>Coldwell</Key>
      <Forenames>N. S.</Forenames>
      <PageNumber>3207</PageNumber>
    </MainItem>
  </ItemGroup>
  <ItemGroup>
    <MainItem>
      <Key>Cole</Key>
      <Forenames>B. M. B.</Forenames>
      <PageNumber>3336</PageNumber>
    </MainItem>
  </ItemGroup>
  <ItemGroup>
    <MainItem>
      <Key>
        <KeyDitto>___ ___</KeyDitto>
      </Key>
      <Forenames>D. H</Forenames>
      <PageNumber>3207</PageNumber>
    </MainItem>
  </ItemGroup>
  <ItemGroup>
    <MainItem>
      <Key>
        <KeyDitto>___</KeyDitto>
      </Key>
      <Forenames>E. G.</Forenames>
      <Text>, Cane</Text>
      <PageNumber>1964</PageNumber>
    </MainItem>
  </ItemGroup>
  <ItemGroup>
    <MainItem>
      <Key>
        <KeyDitto>___ ___</KeyDitto>
      </Key>
      <Forenames>I. R</Forenames>
      <PageNumber>3150</PageNumber>
    </MainItem>
  </ItemGroup>
  <ItemGroup>
    <MainItem>
      <Key>
        <KeyDitto>___ ___</KeyDitto>
      </Key>
      <Forenames>R. C</Forenames>
      <PageNumber>3207</PageNumber>
    </MainItem>
  </ItemGroup>
  <ItemGroup>
    <MainItem>
      <Key>
        <KeyDitto>___ ___</KeyDitto>
      </Key>
      <Forenames>W. R</Forenames>
      <Text>,</Text>
      <PageNumber>3099</PageNumber>
    </MainItem>
  </ItemGroup>
  <ItemGroup>
    <MainItem>
      <Key>Coleman</Key>
      <Forenames>D. G.</Forenames>
      <Text>, Corr</Text>
      <PageNumber>2105</PageNumber>
    </MainItem>
  </ItemGroup>
  <ItemGroup>
    <MainItem>
      <Key>
        <KeyDitto>___ ___ ___</KeyDitto>
      </Key>
      <Forenames>F. G.</Forenames>
      <PageNumber>2831</PageNumber>
    </MainItem>
  </ItemGroup>
  <ItemGroup>
    <MainItem>
      <Key>
        <KeyDitto>___ ___</KeyDitto>
      </Key>
      <Forenames>J. T.</Forenames>
      <PageNumber>3458</PageNumber>
    </MainItem>
  </ItemGroup>
  <ItemGroup>
    <MainItem>
      <Key>
        <KeyDitto>___ ___</KeyDitto>
      </Key>
      <Forenames>M. J.</Forenames>
      <PageNumber>2698</PageNumber>
    </MainItem>
  </ItemGroup>
  <ItemGroup>
    <MainItem>
      <Key>Coles</Key>
      <Forenames>R. J. G.</Forenames>
      <PageNumber>2104</PageNumber>
    </MainItem>
  </ItemGroup>
  <ItemGroup>
    <MainItem>
      <Key>Collee</Key>
      <Forenames>J. G.</Forenames>
      <PageNumber>2768</PageNumber>
    </MainItem>
  </ItemGroup>
  <ItemGroup>
    <MainItem>
      <Key>Collett</Key>
      <Forenames>P. G.</Forenames>
      <PageNumber>3099</PageNumber>
    </MainItem>
  </ItemGroup>
  <ItemGroup>
    <MainItem>
      <Key>Collie</Key>
      <Forenames>A. M.</Forenames>
      <PageNumber>3456</PageNumber>
    </MainItem>
  </ItemGroup>
  <ItemGroup>
    <MainItem>
      <Key>Collier</Key>
      <Forenames>F. C</Forenames>
      <Text>,</Text>
      <PageNumber>2256</PageNumber>
      <PageNumber>2256</PageNumber>
    </MainItem>
  </ItemGroup>
  <ItemGroup>
    <MainItem>
      <Key>
        <KeyDitto>___ ___</KeyDitto>
      </Key>
      <Forenames>J. D.</Forenames>
      <PageNumber>3457</PageNumber>
    </MainItem>
  </ItemGroup>
  <ItemGroup>
    <MainItem>
      <Key>
        <KeyDitto>___ ___</KeyDitto>
      </Key>
      <Forenames>K. W.</Forenames>
      <PageNumber>2482</PageNumber>
    </MainItem>
  </ItemGroup>
  <ItemGroup>
    <MainItem>
      <Key>Collings</Key>
      <Forenames>E. C. T.</Forenames>
      <PageNumber>3521</PageNumber>
    </MainItem>
  </ItemGroup>
  <ItemGroup>
    <MainItem>
      <Key>
        <KeyDitto>___ ___</KeyDitto>
      </Key>
      <Forenames>F.</Forenames>
      <Text>dA</Text>
      <PageNumber>3333</PageNumber>
    </MainItem>
  </ItemGroup>
  <ItemGroup>
    <MainItem>
      <Key>
        <KeyDitto>___ ___</KeyDitto>
      </Key>
      <Forenames>H.</Forenames>
      <PageNumber>2341</PageNumber>
    </MainItem>
  </ItemGroup>
  <ItemGroup>
    <MainItem>
      <Key>
        <KeyDitto>___ ___</KeyDitto>
      </Key>
      <Forenames>T. D.</Forenames>
      <PageNumber>2896</PageNumber>
    </MainItem>
  </ItemGroup>
  <ItemGroup>
    <MainItem>
      <Key>Collingwood</Key>
      <Forenames>T.</Forenames>
      <PageNumber>2105</PageNumber>
    </MainItem>
  </ItemGroup>
  <KeyDitto>___ ___ ...</KeyDitto>
  <KeyDitto>___ ___ ___ ...</KeyDitto>
  <KeyDitto>___ ___ ...</KeyDitto>
  <KeyDitto>___ ___ ...</KeyDitto>
  <KeyDitto>___</KeyDitto>
  <KeyDitto>___ ...</KeyDitto>
  <ItemGroup>
    <MainItem>
      <Key>
        <KeyDitto>___</KeyDitto>
      </Key>
      <Forenames>M.</Forenames>
      <PageNumber>3027</PageNumber>
    </MainItem>
  </ItemGroup>
  <ItemGroup>
    <MainItem>
      <Key>
        <KeyDitto>___ ___</KeyDitto>
      </Key>
      <Forenames>W. E.</Forenames>
      <PageNumber>2895</PageNumber>
    </MainItem>
  </ItemGroup>
  <ItemGroup>
    <MainItem>
      <Key>
        <KeyDitto>-— ___ ___</KeyDitto>
      </Key>
      <Forenames>W. L.</Forenames>
      <PageNumber>2635</PageNumber>
    </MainItem>
  </ItemGroup>
  <ItemGroup>
    <MainItem>
      <Key>Collinson</Key>
      <Forenames>J. C.</Forenames>
      <PageNumber>3522</PageNumber>
    </MainItem>
  </ItemGroup>
  <ItemGroup>
    <MainItem>
      <Key>
        <KeyDitto>___ ___</KeyDitto>
      </Key>
      <Forenames>M.</Forenames>
      <PageNumber>2482</PageNumber>
    </MainItem>
  </ItemGroup>
  <ItemGroup>
    <MainItem>
      <Key>Collis</Key>
      <Forenames>M. D. P.</Forenames>
      <PageNumber>3601</PageNumber>
    </MainItem>
  </ItemGroup>
  <ItemGroup>
    <MainItem>
      <Key>
        <KeyDitto>___ ___ ___</KeyDitto>
      </Key>
      <Forenames>V. W.</Forenames>
      <PageNumber>2340</PageNumber>
    </MainItem>
  </ItemGroup>
  <ItemGroup>
    <MainItem>
      <Key>Collyns</Key>
      <Forenames>A. J.</Forenames>
      <PageNumber>2189</PageNumber>
    </MainItem>
  </ItemGroup>
  <ItemGroup>
    <MainItem>
      <Key>Colt</Key>
      <Forenames>R. H. D.</Forenames>
      <PageNumber>2339</PageNumber>
    </MainItem>
  </ItemGroup>
  <ItemGroup>
    <MainItem>
      <Key>Colfhurst</Key>
      <Forenames>B. H.</Forenames>
      <PageNumber>2695</PageNumber>
    </MainItem>
  </ItemGroup>
  <ItemGroup>
    <MainItem>
      <Key>Colville</Key>
      <Forenames>E. H.</Forenames>
      <PageNumber>2188</PageNumber>
    </MainItem>
  </ItemGroup>
  <ItemGroup>
    <MainItem>
      <Key>Comley</Key>
      <Forenames>B. E. M.</Forenames>
      <PageNumber>2565</PageNumber>
    </MainItem>
  </ItemGroup>
  <SubCategoryTitle>Sub. not. ..</SubCategoryTitle>
  <ItemGroup>
    <MainItem>
      <Key>Coney</Key>
      <Forenames>L. R. H.</Forenames>
      <PageNumber>3521</PageNumber>
    </MainItem>
  </ItemGroup>
  <ItemGroup>
    <MainItem>
      <Key>
        <KeyDitto>___ ___</KeyDitto>
      </Key>
      <Forenames>P. N. H.</Forenames>
      <PageNumber>2035</PageNumber>
    </MainItem>
  </ItemGroup>
  <ItemGroup>
    <MainItem>
      <Key>Conley</Key>
      <Forenames>J. A.</Forenames>
      <PageNumber>2034</PageNumber>
    </MainItem>
  </ItemGroup>
  <ItemGroup>
    <MainItem>
      <Key>Conlon</Key>
      <Forenames>P. C.</Forenames>
      <PageNumber>2340</PageNumber>
    </MainItem>
  </ItemGroup>
  <ItemGroup>
    <MainItem>
      <Key>Conner</Key>
      <Forenames>C. B.</Forenames>
      <PageNumber>2190</PageNumber>
    </MainItem>
  </ItemGroup>
  <ItemGroup>
    <MainItem>
      <Key>Connolly</Key>
      <Forenames>T. J.</Forenames>
      <PageNumber>1861</PageNumber>
    </MainItem>
  </ItemGroup>
  <ItemGroup>
    <MainItem>
      <Key>Connors</Key>
      <Forenames>J. A. B</Forenames>
      <Text>, Constable, J. A</Text>
      <PageNumber>3520</PageNumber>
      <PageNumber>3600</PageNumber>
    </MainItem>
  </ItemGroup>
  <ItemGroup>
    <MainItem>
      <Key>Constant</Key>
      <Forenames>M.</Forenames>
      <PageNumber>3098</PageNumber>
    </MainItem>
  </ItemGroup>
  <ItemGroup>
    <MainItem>
      <Key>
        <KeyDitto>___ ___ ___</KeyDitto>
      </Key>
      <Forenames>M. E.</Forenames>
      <PageNumber>2189</PageNumber>
    </MainItem>
  </ItemGroup>
  <ItemGroup>
    <MainItem>
      <Key>Conway</Key>
      <Forenames>M. J.</Forenames>
      <PageNumber>1861</PageNumber>
    </MainItem>
  </ItemGroup>
  <ItemGroup>
    <MainItem>
      <Key>Cook</Key>
      <Forenames>A. T.</Forenames>
      <PageNumber>2410</PageNumber>
    </MainItem>
  </ItemGroup>
  <ItemGroup>
    <MainItem>
      <Key>
        <KeyDitto>___ ___</KeyDitto>
      </Key>
      <Forenames>H. R. C. C .</Forenames>
      <PageNumber>2256</PageNumber>
    </MainItem>
  </ItemGroup>
  <ItemGroup>
    <MainItem>
      <Key>
        <KeyDitto>___ ___</KeyDitto>
      </Key>
      <Forenames>J. C.</Forenames>
      <PageNumber>2481</PageNumber>
    </MainItem>
  </ItemGroup>
  <ItemGroup>
    <MainItem>
      <Key>
        <KeyDitto>___ ___ ___ ___</KeyDitto>
      </Key>
      <Forenames>M. R.</Forenames>
      <PageNumber>2483</PageNumber>
    </MainItem>
  </ItemGroup>
  <ItemGroup>
    <MainItem>
      <Key>
        <KeyDitto>___ ___ ___</KeyDitto>
      </Key>
      <Forenames>N. F. B.</Forenames>
      <PageNumber>3336</PageNumber>
    </MainItem>
  </ItemGroup>
  <ItemGroup>
    <MainItem>
      <Key>
        <KeyDitto>___ ___</KeyDitto>
      </Key>
      <Forenames>W.</Forenames>
      <PageNumber>3599</PageNumber>
    </MainItem>
  </ItemGroup>
  <ItemGroup>
    <MainItem>
      <Key>Cooke</Key>
      <Forenames>J. R.</Forenames>
      <PageNumber>2341</PageNumber>
    </MainItem>
  </ItemGroup>
  <ItemGroup>
    <MainItem>
      <Key>
        <KeyDitto>___ ___</KeyDitto>
      </Key>
      <Forenames>R. T.</Forenames>
      <PageNumber>2105</PageNumber>
    </MainItem>
  </ItemGroup>
  <ItemGroup>
    <MainItem>
      <Key>Coombes</Key>
      <Forenames>S. K.</Forenames>
      <PageNumber>2191</PageNumber>
    </MainItem>
    <KeyDitto>___ ___ ...</KeyDitto>
    <SubItem>
      <Text>F. W</Text>
      <PageNumber>2409</PageNumber>
    </SubItem>
  </ItemGroup>
  <ItemGroup>
    <MainItem>
      <Key>
        <KeyDitto>___ ___</KeyDitto>
      </Key>
      <Forenames>G. D.</Forenames>
      <PageNumber>3458</PageNumber>
    </MainItem>
  </ItemGroup>
  <ItemGroup>
    <MainItem>
      <Key>
        <KeyDitto>___ ___</KeyDitto>
      </Key>
      <Forenames>H. A.</Forenames>
      <PageNumber>3455</PageNumber>
    </MainItem>
  </ItemGroup>
  <ItemGroup>
    <MainItem>
      <Key>
        <KeyDitto>___ ___</KeyDitto>
      </Key>
      <Forenames>J.</Forenames>
      <PageNumber>2829</PageNumber>
    </MainItem>
  </ItemGroup>
  <ItemGroup>
    <MainItem>
      <Key>
        <KeyDitto>___ ___</KeyDitto>
      </Key>
      <Forenames>J. H.</Forenames>
      <PageNumber>3522</PageNumber>
    </MainItem>
  </ItemGroup>
  <ItemGroup>
    <MainItem>
      <Key>
        <KeyDitto>___ ___</KeyDitto>
      </Key>
      <Forenames>J. W.</Forenames>
      <PageNumber>2034</PageNumber>
    </MainItem>
  </ItemGroup>
  <ItemGroup>
    <MainItem>
      <Key>
        <KeyDitto>___ ___</KeyDitto>
      </Key>
      <Forenames>K. A.</Forenames>
      <PageNumber>2105</PageNumber>
      <PageNumber>3210</PageNumber>
    </MainItem>
  </ItemGroup>
  <ItemGroup>
    <MainItem>
      <Key>
        <KeyDitto>___ ___</KeyDitto>
      </Key>
      <Forenames>M. S.</Forenames>
      <PageNumber>2190</PageNumber>
    </MainItem>
  </ItemGroup>
  <ItemGroup>
    <MainItem>
      <Key>
        <KeyDitto>___ ___ ___</KeyDitto>
      </Key>
      <Forenames>R. G.</Forenames>
      <PageNumber>3333</PageNumber>
    </MainItem>
  </ItemGroup>
  <ItemGroup>
    <MainItem>
      <Key>
        <KeyDitto>___ ___ ___</KeyDitto>
      </Key>
      <Forenames>R. P.</Forenames>
      <PageNumber>3393</PageNumber>
    </MainItem>
  </ItemGroup>
  <ItemGroup>
    <MainItem>
      <Key>
        <KeyDitto>___ ___</KeyDitto>
      </Key>
      <Forenames>W. F.</Forenames>
      <PageNumber>3264</PageNumber>
    </MainItem>
  </ItemGroup>
  <ItemGroup>
    <MainItem>
      <Key>
        <KeyDitto>___ ___</KeyDitto>
      </Key>
      <Forenames>W. F. H.</Forenames>
      <PageNumber>2188</PageNumber>
    </MainItem>
  </ItemGroup>
  <ItemGroup>
    <MainItem>
      <Key>
        <KeyDitto>___ ___</KeyDitto>
      </Key>
      <Forenames>W. M. W.</Forenames>
      <PageNumber>1863</PageNumber>
    </MainItem>
  </ItemGroup>
  <ItemGroup>
    <MainItem>
      <Key>Copeland</Key>
      <Forenames>A.</Forenames>
      <PageNumber>2035</PageNumber>
    </MainItem>
  </ItemGroup>
  <ItemGroup>
    <MainItem>
      <Key>
        <KeyDitto>___ ___</KeyDitto>
      </Key>
      <Forenames>F. T.</Forenames>
      <PageNumber>3333</PageNumber>
    </MainItem>
  </ItemGroup>
  <ItemGroup>
    <MainItem>
      <Key>Coppen</Key>
      <Forenames>T. E.</Forenames>
      <PageNumber>2410</PageNumber>
    </MainItem>
  </ItemGroup>
  <ItemGroup>
    <MainItem>
      <Key>Copplestone</Key>
      <Forenames>S.</Forenames>
      <PageNumber>3263</PageNumber>
    </MainItem>
  </ItemGroup>
  <ItemGroup>
    <MainItem>
      <Key>Corbett</Key>
      <Forenames>A. D.</Forenames>
      <PageNumber>3100</PageNumber>
    </MainItem>
  </ItemGroup>
  <KeyDitto>___ ___ ...</KeyDitto>
  <ItemGroup>
    <MainItem>
      <Key>Corcoran</Key>
      <Forenames>J. A.</Forenames>
      <PageNumber>2341</PageNumber>
    </MainItem>
  </ItemGroup>
  <ItemGroup>
    <MainItem>
      <Key>Corden</Key>
      <Forenames>I. R.</Forenames>
      <PageNumber>3098</PageNumber>
    </MainItem>
  </ItemGroup>
  <ItemGroup>
    <MainItem>
      <Key>Corder</Key>
      <Forenames>M.</Forenames>
      <PageNumber>3263</PageNumber>
    </MainItem>
  </ItemGroup>
  <ItemGroup>
    <MainItem>
      <Key>Corderoy</Key>
      <Forenames>O.</Forenames>
      <PageNumber>2342</PageNumber>
    </MainItem>
  </ItemGroup>
  <ItemGroup>
    <MainItem>
      <Key>Corfield</Key>
      <Forenames>E. J. M</Forenames>
      <Text>,</Text>
      <PageNumber>2193</PageNumber>
    </MainItem>
  </ItemGroup>
  <ItemGroup>
    <MainItem>
      <Key>Corley</Key>
      <Forenames>M. A.</Forenames>
      <PageNumber>2188</PageNumber>
    </MainItem>
  </ItemGroup>
  <ItemGroup>
    <MainItem>
      <Key>Cormack</Key>
      <Forenames>R. A.</Forenames>
      <PageNumber>3261</PageNumber>
    </MainItem>
  </ItemGroup>
  <ItemGroup>
    <MainItem>
      <Key>Corner</Key>
      <Forenames>B. S.</Forenames>
      <PageNumber>2831</PageNumber>
    </MainItem>
  </ItemGroup>
  <ItemGroup>
    <MainItem>
      <Key>Comes</Key>
      <Forenames>B.</Forenames>
      <PageNumber>2341</PageNumber>
    </MainItem>
  </ItemGroup>
  <ItemGroup>
    <MainItem>
      <Key>Cornish</Key>
      <Forenames>F. D.</Forenames>
      <PageNumber>3263</PageNumber>
    </MainItem>
  </ItemGroup>
  <ItemGroup>
    <MainItem>
      <Key>Corsane</Key>
      <Forenames>L. H. Coryton</Forenames>
      <Text>, R. H. O</Text>
      <PageNumber>2033</PageNumber>
    </MainItem>
  </ItemGroup>
  <ItemGroup>
    <MainItem>
      <Key>Costar</Key>
      <Forenames>F</Forenames>
      <PageNumber>3520</PageNumber>
    </MainItem>
  </ItemGroup>
  <ItemGroup>
    <MainItem>
      <Key>Cottelle</Key>
      <Forenames>A. C.</Forenames>
      <PageNumber>3336</PageNumber>
    </MainItem>
  </ItemGroup>
  <ItemGroup>
    <MainItem>
      <Key>Cotton</Key>
      <Forenames>H. E. M .</Forenames>
      <PageNumber>1861</PageNumber>
    </MainItem>
  </ItemGroup>
  <ItemGroup>
    <MainItem>
      <Key>
        <KeyDitto>___ ___</KeyDitto>
      </Key>
      <Forenames>J. D.</Forenames>
      <PageNumber>2189</PageNumber>
    </MainItem>
  </ItemGroup>
  <ItemGroup>
    <MainItem>
      <Key>Coullie</Key>
      <Forenames>K. I.</Forenames>
      <PageNumber>3027</PageNumber>
    </MainItem>
  </ItemGroup>
  <ItemGroup>
    <MainItem>
      <Key>Couper</Key>
      <Forenames>T. F.</Forenames>
      <PageNumber>2695</PageNumber>
    </MainItem>
  </ItemGroup>
  <ItemGroup>
    <MainItem>
      <Key>Courage</Key>
      <Forenames>P. E.</Forenames>
      <PageNumber>2339</PageNumber>
    </MainItem>
  </ItemGroup>
  <ItemGroup>
    <MainItem>
      <Key>Court</Key>
      <Forenames>R. E.</Forenames>
      <PageNumber>2189</PageNumber>
    </MainItem>
  </ItemGroup>
  <ItemGroup>
    <MainItem>
      <Key>Courtenay-Bishop</Key>
      <Forenames>J. G.</Forenames>
      <PageNumber>3100</PageNumber>
    </MainItem>
  </ItemGroup>
  <ItemGroup>
    <MainItem>
      <Key>Courtier</Key>
      <Forenames>L. D.</Forenames>
      <PageNumber>3264</PageNumber>
    </MainItem>
  </ItemGroup>
  <ItemGroup>
    <MainItem>
      <Key>Couthbert</Key>
      <Forenames>G. E.</Forenames>
      <PageNumber>1965</PageNumber>
    </MainItem>
  </ItemGroup>
  <ItemGroup>
    <MainItem>
      <Key>Coveney</Key>
      <Forenames>L. G.</Forenames>
      <PageNumber>2479</PageNumber>
    </MainItem>
  </ItemGroup>
  <ItemGroup>
    <MainItem>
      <Key>Coverman</Key>
      <Forenames>J</Forenames>
      <PageNumber>3455</PageNumber>
    </MainItem>
  </ItemGroup>
  <ItemGroup>
    <MainItem>
      <Key>Cowan</Key>
      <Forenames>C. H.</Forenames>
      <PageNumber>1861</PageNumber>
    </MainItem>
  </ItemGroup>
  <ItemGroup>
    <MainItem>
      <Key>
        <KeyDitto>___ ___ ___</KeyDitto>
      </Key>
      <Forenames>C</Forenames>
      <Text>R</Text>
      <PageNumber>2102</PageNumber>
    </MainItem>
  </ItemGroup>
  <ItemGroup>
    <MainItem>
      <Key>Cowen</Key>
      <Forenames>J</Forenames>
      <PageNumber>2566</PageNumber>
    </MainItem>
  </ItemGroup>
  <ItemGroup>
    <MainItem>
      <Key>Cowie</Key>
      <Forenames>W. D.</Forenames>
      <PageNumber>2103</PageNumber>
    </MainItem>
  </ItemGroup>
  <ItemGroup>
    <MainItem>
      <Key>Cowley</Key>
      <Forenames>J. C.</Forenames>
      <PageNumber>2480</PageNumber>
    </MainItem>
  </ItemGroup>
  <ItemGroup>
    <MainItem>
      <Key>
        <KeyDitto>___ ___ ___</KeyDitto>
      </Key>
      <Forenames>M. D</Forenames>
      <PageNumber>2567</PageNumber>
    </MainItem>
  </ItemGroup>
  <ItemGroup>
    <MainItem>
      <Key>Cowper</Key>
      <Forenames>T. S.</Forenames>
      <PageNumber>2566</PageNumber>
    </MainItem>
  </ItemGroup>
  <ItemGroup>
    <MainItem>
      <Key>Cox</Key>
      <Forenames>B. S</Forenames>
      <PageNumber>3208</PageNumber>
    </MainItem>
  </ItemGroup>
  <ItemGroup>
    <MainItem>
      <Key>
        <KeyDitto>___ ___ ___</KeyDitto>
      </Key>
      <Forenames>G. A</Forenames>
      <PageNumber>2104</PageNumber>
    </MainItem>
  </ItemGroup>
  <ItemGroup>
    <MainItem>
      <Key>
        <KeyDitto>___ ___ ___</KeyDitto>
      </Key>
      <Forenames>G. S. R.</Forenames>
      <PageNumber>2190</PageNumber>
    </MainItem>
  </ItemGroup>
  <KeyDitto>___ —___ ___</KeyDitto>
  <ItemGroup>
    <MainItem>
      <Key>
        <KeyDitto>___ ___</KeyDitto>
      </Key>
      <Forenames>L. T</Forenames>
      <PageNumber>2189</PageNumber>
    </MainItem>
  </ItemGroup>
  <ItemGroup>
    <MainItem>
      <Key>
        <KeyDitto>___ ___ ___</KeyDitto>
      </Key>
      <Forenames>P. C. B.</Forenames>
      <PageNumber>2410</PageNumber>
    </MainItem>
  </ItemGroup>
  <ItemGroup>
    <MainItem>
      <Key>
        <KeyDitto>___ ___</KeyDitto>
      </Key>
      <Forenames>R. C. R.</Forenames>
      <PageNumber>3335</PageNumber>
    </MainItem>
  </ItemGroup>
  <ItemGroup>
    <MainItem>
      <Key>
        <KeyDitto>___ ___ ___</KeyDitto>
      </Key>
      <Forenames>R. J</Forenames>
      <PageNumber>3209</PageNumber>
    </MainItem>
  </ItemGroup>
  <ItemGroup>
    <MainItem>
      <Key>
        <KeyDitto>___ ___ ___</KeyDitto>
      </Key>
      <Forenames>W. F. H.</Forenames>
      <PageNumber>1862</PageNumber>
    </MainItem>
  </ItemGroup>
  <ItemGroup>
    <MainItem>
      <Key>
        <KeyDitto>___ ___ ___</KeyDitto>
      </Key>
      <Forenames>W. H. A. C.</Forenames>
      <PageNumber>3264</PageNumber>
    </MainItem>
  </ItemGroup>
  <ItemGroup>
    <MainItem>
      <Key>Crabbe</Key>
      <Forenames>J. R.</Forenames>
      <PageNumber>2697</PageNumber>
    </MainItem>
  </ItemGroup>
  <ItemGroup>
    <MainItem>
      <Key>Crabtree</Key>
      <Forenames>D. T.</Forenames>
      <PageNumber>2339</PageNumber>
    </MainItem>
  </ItemGroup>
  <ItemGroup>
    <MainItem>
      <Key>
        <KeyDitto>___ ___ ___</KeyDitto>
      </Key>
      <Forenames>T. W</Forenames>
      <PageNumber>3099</PageNumber>
    </MainItem>
  </ItemGroup>
  <ItemGroup>
    <MainItem>
      <Key>Craddock</Key>
      <Forenames>D. V. A.</Forenames>
      <PageNumber>2189</PageNumber>
    </MainItem>
  </ItemGroup>
  <ItemGroup>
    <MainItem>
      <Key>Crafer</Key>
      <Forenames>D. M.</Forenames>
      <PageNumber>2036</PageNumber>
    </MainItem>
  </ItemGroup>
  <ItemGroup>
    <MainItem>
      <Key>Craft</Key>
      <Forenames>J. R. de B</Forenames>
      <PageNumber>2189</PageNumber>
    </MainItem>
  </ItemGroup>
  <ItemGroup>
    <MainItem>
      <Key>Craig</Key>
      <Forenames>A. G</Forenames>
      <PageNumber>2831</PageNumber>
    </MainItem>
  </ItemGroup>
  <ItemGroup>
    <MainItem>
      <Key>
        <KeyDitto>___ ___</KeyDitto>
      </Key>
      <Forenames>A. J</Forenames>
      <PageNumber>2698</PageNumber>
    </MainItem>
  </ItemGroup>
  <ItemGroup>
    <MainItem>
      <Key>
        <KeyDitto>___ ___ ___</KeyDitto>
      </Key>
      <Forenames>D. J</Forenames>
      <PageNumber>3151</PageNumber>
    </MainItem>
  </ItemGroup>
  <ItemGroup>
    <MainItem>
      <Key>
        <KeyDitto>___ ___</KeyDitto>
      </Key>
      <Forenames>J. M</Forenames>
      <PageNumber>2483</PageNumber>
    </MainItem>
  </ItemGroup>
  <ItemGroup>
    <MainItem>
      <Key>
        <KeyDitto>___ ___</KeyDitto>
      </Key>
      <Forenames>L. J. J.</Forenames>
      <PageNumber>3601</PageNumber>
    </MainItem>
  </ItemGroup>
  <ItemGroup>
    <MainItem>
      <Key>
        <KeyDitto>___ ___ ___</KeyDitto>
      </Key>
      <Forenames>T. H. R.</Forenames>
      <PageNumber>2479</PageNumber>
    </MainItem>
  </ItemGroup>
  <ItemGroup>
    <MainItem>
      <Key>
        <KeyDitto>___ ___</KeyDitto>
      </Key>
      <Forenames>W. R. C.</Forenames>
      <PageNumber>2190</PageNumber>
    </MainItem>
  </ItemGroup>
  <ItemGroup>
    <MainItem>
      <Key>Craig-McFeely</Key>
      <Forenames>C. P. M.</Forenames>
      <PageNumber>3264</PageNumber>
    </MainItem>
  </ItemGroup>
  <ItemGroup>
    <MainItem>
      <Key>Craig-Mooney</Key>
      <Forenames>A.</Forenames>
      <Text>, Sub. not</Text>
      <PageNumber>1965</PageNumber>
    </MainItem>
  </ItemGroup>
  <ItemGroup>
    <MainItem>
      <Key>Cram</Key>
      <Forenames>L. W</Forenames>
      <PageNumber>2896</PageNumber>
    </MainItem>
  </ItemGroup>
  <ItemGroup>
    <MainItem>
      <Key>Crammond</Key>
      <Forenames>I. R.</Forenames>
      <Text>, Sub. not</Text>
      <PageNumber>3205</PageNumber>
    </MainItem>
  </ItemGroup>
  <ItemGroup>
    <MainItem>
      <Key>Crampton</Key>
      <Forenames>G. P. C. R.</Forenames>
      <PageNumber>2566</PageNumber>
    </MainItem>
  </ItemGroup>
  <ItemGroup>
    <MainItem>
      <Key>Craven</Key>
      <Forenames>J. C. R.</Forenames>
      <PageNumber>1933</PageNumber>
    </MainItem>
  </ItemGroup>
  <ItemGroup>
    <MainItem>
      <Key>Crawford</Key>
      <Forenames>D. A. B.</Forenames>
      <Text>, Sub. not</Text>
      <PageNumber>3602</PageNumber>
    </MainItem>
  </ItemGroup>
  <ItemGroup>
    <MainItem>
      <Key>
        <KeyDitto>___ ___</KeyDitto>
      </Key>
      <Forenames>H. E</Forenames>
      <PageNumber>1863</PageNumber>
    </MainItem>
  </ItemGroup>
  <ItemGroup>
    <MainItem>
      <Key>
        <KeyDitto>___ ___</KeyDitto>
      </Key>
      <Forenames>J. A</Forenames>
      <PageNumber>2409</PageNumber>
    </MainItem>
  </ItemGroup>
  <ItemGroup>
    <MainItem>
      <Key>
        <KeyDitto>___ ___</KeyDitto>
      </Key>
      <Forenames>J. H.</Forenames>
      <Text>(Foresters)</Text>
      <PageNumber>2481</PageNumber>
    </MainItem>
  </ItemGroup>
  <ItemGroup>
    <MainItem>
      <Key>
        <KeyDitto>___ ___</KeyDitto>
      </Key>
      <Forenames>J. H.</Forenames>
      <Text>(Intell. C.)</Text>
      <PageNumber>2341</PageNumber>
    </MainItem>
  </ItemGroup>
  <ItemGroup>
    <MainItem>
      <Key>Crawford-Clarke</Key>
      <Forenames>R. D.</Forenames>
      <PageNumber>2036</PageNumber>
    </MainItem>
  </ItemGroup>
  <ItemGroup>
    <MainItem>
      <Key>Crawshaw</Key>
      <Forenames>A. F.</Forenames>
      <PageNumber>2698</PageNumber>
    </MainItem>
  </ItemGroup>
  <ItemGroup>
    <MainItem>
      <Key>Creasey</Key>
      <Forenames>R. H.</Forenames>
      <PageNumber>2566</PageNumber>
    </MainItem>
  </ItemGroup>
  <ItemGroup>
    <MainItem>
      <Key>Crees</Key>
      <Forenames>H</Forenames>
      <PageNumber>3520</PageNumber>
    </MainItem>
  </ItemGroup>
  <ItemGroup>
    <MainItem>
      <Key>Creighton</Key>
      <Forenames>C. A.</Forenames>
      <PageNumber>3097</PageNumber>
    </MainItem>
  </ItemGroup>
  <ItemGroup>
    <MainItem>
      <Key>Cresswell</Key>
      <Forenames>R. S.</Forenames>
      <PageNumber>3520</PageNumber>
    </MainItem>
  </ItemGroup>
  <ItemGroup>
    <MainItem>
      <Key>Crewdson</Key>
      <Forenames>R. J. A.</Forenames>
      <PageNumber>2036</PageNumber>
    </MainItem>
  </ItemGroup>
  <ItemGroup>
    <MainItem>
      <Key>Crinean</Key>
      <Forenames>W. H.</Forenames>
      <PageNumber>3027</PageNumber>
    </MainItem>
  </ItemGroup>
  <ItemGroup>
    <MainItem>
      <Key>Cringle</Key>
      <Forenames>R. C.</Forenames>
      <PageNumber>3521</PageNumber>
    </MainItem>
  </ItemGroup>
  <ItemGroup>
    <MainItem>
      <Key>Criper</Key>
      <Forenames>H. F.</Forenames>
      <PageNumber>3026</PageNumber>
    </MainItem>
  </ItemGroup>
  <ItemGroup>
    <MainItem>
      <Key>Crisp</Key>
      <Forenames>D. J.</Forenames>
      <PageNumber>2341</PageNumber>
    </MainItem>
  </ItemGroup>
  <ItemGroup>
    <MainItem>
      <Key>
        <KeyDitto>___ ___ ___</KeyDitto>
      </Key>
      <Forenames>J. E</Forenames>
      <PageNumber>3206</PageNumber>
    </MainItem>
  </ItemGroup>
  <ItemGroup>
    <MainItem>
      <Key>Criswick</Key>
      <Forenames>V. G.</Forenames>
      <PageNumber>3207</PageNumber>
    </MainItem>
  </ItemGroup>
  <ItemGroup>
    <MainItem>
      <Key>Critchley</Key>
      <Forenames>L. P.</Forenames>
      <PageNumber>2479</PageNumber>
    </MainItem>
  </ItemGroup>
  <ItemGroup>
    <MainItem>
      <Key>Croce</Key>
      <Forenames>J. N</Forenames>
      <PageNumber>1862</PageNumber>
    </MainItem>
  </ItemGroup>
  <ItemGroup>
    <MainItem>
      <Key>Crocker</Key>
      <Forenames>L. H.</Forenames>
      <PageNumber>2101</PageNumber>
    </MainItem>
  </ItemGroup>
  <ItemGroup>
    <MainItem>
      <Key>Crockford</Key>
      <Text>CM</Text>
      <PageNumber>2830</PageNumber>
    </MainItem>
  </ItemGroup>
  <ItemGroup>
    <MainItem>
      <Key>
        <KeyDitto>___ ___ ___ ___</KeyDitto>
      </Key>
      <Forenames>W. A</Forenames>
      <PageNumber>3334</PageNumber>
    </MainItem>
  </ItemGroup>
  <ItemGroup>
    <MainItem>
      <Key>Croker</Key>
      <Forenames>G. W.</Forenames>
      <PageNumber>2767</PageNumber>
    </MainItem>
  </ItemGroup>
  <ItemGroup>
    <MainItem>
      <Key>Croll</Key>
      <Forenames>R.</Forenames>
      <Text>MQ</Text>
      <PageNumber>3264</PageNumber>
    </MainItem>
  </ItemGroup>
  <ItemGroup>
    <MainItem>
      <Key>Crombie</Key>
      <Forenames>A. J. W.</Forenames>
      <PageNumber>2187</PageNumber>
    </MainItem>
  </ItemGroup>
  <ItemGroup>
    <MainItem>
      <Key>Cronshaw</Key>
      <Forenames>J. W.</Forenames>
      <PageNumber>2104</PageNumber>
    </MainItem>
  </ItemGroup>
  <ItemGroup>
    <MainItem>
      <Key>Crook</Key>
      <Forenames>B. F.</Forenames>
      <PageNumber>2190</PageNumber>
    </MainItem>
  </ItemGroup>
  <ItemGroup>
    <MainItem>
      <Key>
        <KeyDitto>___ ___</KeyDitto>
      </Key>
      <Forenames>J. H</Forenames>
      <PageNumber>3336</PageNumber>
    </MainItem>
  </ItemGroup>
  <ItemGroup>
    <MainItem>
      <Key>Crooke</Key>
      <Forenames>M. J. P.</Forenames>
      <PageNumber>2188</PageNumber>
    </MainItem>
  </ItemGroup>
  <ItemGroup>
    <MainItem>
      <Key>Crookenden</Key>
      <Forenames>G. W. D.</Forenames>
      <PageNumber>3333</PageNumber>
    </MainItem>
  </ItemGroup>
  <ItemGroup>
    <MainItem>
      <Key>Crooks</Key>
      <Forenames>W. G.</Forenames>
      <PageNumber>3336</PageNumber>
    </MainItem>
  </ItemGroup>
  <ItemGroup>
    <MainItem>
      <Key>Crookshank</Key>
      <Forenames>R. F. A.</Forenames>
      <PageNumber>2191</PageNumber>
    </MainItem>
  </ItemGroup>
  <ItemGroup>
    <MainItem>
      <Key>Crosby</Key>
      <Forenames>A. E.</Forenames>
      <PageNumber>2103</PageNumber>
      <PageNumber>2103</PageNumber>
    </MainItem>
  </ItemGroup>
  <ItemGroup>
    <MainItem>
      <Key>Cross</Key>
      <Forenames>A. G</Forenames>
      <PageNumber>2566</PageNumber>
    </MainItem>
  </ItemGroup>
  <ItemGroup>
    <MainItem>
      <Key>
        <KeyDitto>___ ___</KeyDitto>
      </Key>
      <Forenames>H. C</Forenames>
      <PageNumber>2257</PageNumber>
    </MainItem>
  </ItemGroup>
  <ItemGroup>
    <MainItem>
      <Key>
        <KeyDitto>___ ___ ___</KeyDitto>
      </Key>
      <Forenames>N.</Forenames>
      <PageNumber>3026</PageNumber>
      <PageNumber>3026</PageNumber>
    </MainItem>
  </ItemGroup>
  <ItemGroup>
    <MainItem>
      <Key>
        <KeyDitto>___ ___</KeyDitto>
      </Key>
      <Forenames>R. A. P.</Forenames>
      <PageNumber>2481</PageNumber>
    </MainItem>
  </ItemGroup>
  <ItemGroup>
    <MainItem>
      <Key>Crosland-Taylor</Key>
      <Forenames>P. J.</Forenames>
      <PageNumber>2768</PageNumber>
    </MainItem>
  </ItemGroup>
  <ItemGroup>
    <MainItem>
      <Key>Crossan</Key>
      <Forenames>L. J.</Forenames>
      <PageNumber>3027</PageNumber>
    </MainItem>
  </ItemGroup>
  <ItemGroup>
    <MainItem>
      <Key>Crouch</Key>
      <Forenames>C. A. A.</Forenames>
      <PageNumber>1931</PageNumber>
    </MainItem>
  </ItemGroup>
  <ItemGroup>
    <MainItem>
      <Key>Crowder</Key>
      <Forenames>M</Forenames>
      <PageNumber>3099</PageNumber>
    </MainItem>
  </ItemGroup>
  <ItemGroup>
    <MainItem>
      <Key>Crowther</Key>
      <Forenames>J. E.</Forenames>
      <PageNumber>2035</PageNumber>
    </MainItem>
  </ItemGroup>
  <ItemGroup>
    <MainItem>
      <Key>Croysdale</Key>
      <Forenames>J. B.</Forenames>
      <PageNumber>3208</PageNumber>
    </MainItem>
  </ItemGroup>
  <ItemGroup>
    <MainItem>
      <Key>Cruddas</Key>
      <Forenames>J. M.</Forenames>
      <PageNumber>2341</PageNumber>
    </MainItem>
  </ItemGroup>
  <ItemGroup>
    <MainItem>
      <Key>Cruickshank</Key>
      <Forenames>I. G. C.</Forenames>
      <PageNumber>2831</PageNumber>
    </MainItem>
  </ItemGroup>
  <ItemGroup>
    <MainItem>
      <Key>
        <KeyDitto>___ ___</KeyDitto>
      </Key>
      <Forenames>R. G</Forenames>
      <PageNumber>2898</PageNumber>
    </MainItem>
  </ItemGroup>
  <ItemGroup>
    <MainItem>
      <Key>Cubbage</Key>
      <Forenames>J.</Forenames>
      <Text>McC</Text>
      <PageNumber>2103</PageNumber>
    </MainItem>
  </ItemGroup>
  <KeyDitto>___ ___ ___</KeyDitto>
</Index>

